dataembedder/__init__.py
dataembedder/dataembedder.py
dataembedder-0.5.1.dist-info/LICENSE
dataembedder-0.5.1.dist-info/METADATA
dataembedder-0.5.1.dist-info/WHEEL
dataembedder-0.5.1.dist-info/top_level.txt
dataembedder-0.5.1.dist-info/RECORD
