Metadata-Version: 2.1
Name: dataembedder
Version: 0.5.1
Summary: Python library for embedding data and models in anatomical scaffolds using Zinc
Home-page: https://github.com/ABI-Software/dataembedder
Author: Auckland Bioengineering Institute
Author-email: r.christie@auckland.ac.nz
License: Apache Software License
Classifier: Development Status :: 3 - Alpha
Classifier: Programming Language :: Python
Classifier: Topic :: Scientific/Engineering :: Medical Science Apps.
License-File: LICENSE
Requires-Dist: cmlibs.utils >=0.6
Requires-Dist: cmlibs.zinc >=4.0
